altai/__init__.py
altai/exceptions.py
altai/saving.py
altai/version.py
altai/api/__init__.py
altai/api/defaults.py
altai/api/interfaces.py
altai/api/tests/__init__.py
altai/api/tests/test_interfaces.py
altai/confidence/__init__.py
altai/confidence/model_linearity.py
altai/confidence/trustscore.py
altai/confidence/tests/__init__.py
altai/confidence/tests/test_model_linearity.py
altai/confidence/tests/test_trustscore.py
altai/data/cats.tar.gz
altai/datasets/__init__.py
altai/datasets/default.py
altai/datasets/tensorflow.py
altai/datasets/tests/__init__.py
altai/datasets/tests/test_datasets.py
altai/explainers/__init__.py
altai/explainers/ale.py
altai/explainers/cem.py
altai/explainers/cfproto.py
altai/explainers/cfrl_base.py
altai/explainers/cfrl_tabular.py
altai/explainers/counterfactual.py
altai/explainers/integrated_gradients.py
altai/explainers/partial_dependence.py
altai/explainers/pd_variance.py
altai/explainers/permutation_importance.py
altai/explainers/shap_wrappers.py
altai/explainers/anchors/__init__.py
altai/explainers/anchors/anchor_base.py
altai/explainers/anchors/anchor_explanation.py
altai/explainers/anchors/anchor_image.py
altai/explainers/anchors/anchor_tabular.py
altai/explainers/anchors/anchor_tabular_distributed.py
altai/explainers/anchors/anchor_text.py
altai/explainers/anchors/language_model_text_sampler.py
altai/explainers/anchors/text_samplers.py
altai/explainers/backends/__init__.py
altai/explainers/backends/cfrl_base.py
altai/explainers/backends/cfrl_tabular.py
altai/explainers/backends/pytorch/__init__.py
altai/explainers/backends/pytorch/cfrl_base.py
altai/explainers/backends/pytorch/cfrl_tabular.py
altai/explainers/backends/tensorflow/__init__.py
altai/explainers/backends/tensorflow/cfrl_base.py
altai/explainers/backends/tensorflow/cfrl_tabular.py
altai/explainers/similarity/__init__.py
altai/explainers/similarity/base.py
altai/explainers/similarity/grad.py
altai/explainers/similarity/metrics.py
altai-0.9.7.dev0.dist-info/METADATA
altai-0.9.7.dev0.dist-info/WHEEL
altai-0.9.7.dev0.dist-info/top_level.txt
altai-0.9.7.dev0.dist-info/RECORD
